pychs/__init__.py
pychs/chs_iwls.py
pychs/const.py
pychs-0.2.2.dist-info/LICENSE.txt
pychs-0.2.2.dist-info/METADATA
pychs-0.2.2.dist-info/WHEEL
pychs-0.2.2.dist-info/top_level.txt
pychs-0.2.2.dist-info/RECORD
